{
  "name": {
    "de": "Education Credential Exporter (Demo)",
    "en": "Education Credential Exporter (Demo)"
  },
  "short_name": {
    "de": "Education Credential Exporter",
    "en": "Education Credential Exporter"
  },
  "description": {
    "de": "Mit dieser Applikation kannst du digitale, verifizierbare Zertifikate für deine LV Noten und Abschlüsse erstellen.",
    "en": "Using this application, you can retrieve a digital and secure version of your diplomas and grades of indiviual courses."
  },
  "routing_name": "vc4sm-frontend",
  "activities": [
    {"path": "did-auth.metadata.json"},
    {"path": "issue-diploma.metadata.json"},
    {"path": "issue-grades.metadata.json"},
    {"path": "verify-vc.metadata.json"}
  ],
  "attributes": []
}
